regolith_subfunctions/__init__.py
regolith_subfunctions/py.typed
regolith_subfunctions-1.4.0.dist-info/LICENSE
regolith_subfunctions-1.4.0.dist-info/METADATA
regolith_subfunctions-1.4.0.dist-info/WHEEL
regolith_subfunctions-1.4.0.dist-info/top_level.txt
regolith_subfunctions-1.4.0.dist-info/RECORD
