Metadata-Version: 2.2
Name: regolith-subfunctions
Version: 1.4.0
Summary: A Python package for easier reuseability of the Subfunctions Regolith filter for Minecraft Bedrock Edition
Author: Nusiq
License: MIT
Project-URL: Source, https://github.com/Nusiq/regolith-subfunctions/tree/master
Classifier: Development Status :: 5 - Production/Stable
Classifier: License :: OSI Approved :: MIT License
Classifier: Programming Language :: Python :: 3.10
Requires-Python: >=3.10
License-File: LICENSE
